LICENSE
MANIFEST.in
README
README.md
setup.cfg
setup.py
./bin/stolos-submit
stolos/__init__.py
stolos/__main__.py
stolos/api.py
stolos/argparse_shared.py
stolos/exceptions.py
stolos/initializer.py
stolos/runner.py
stolos/util.py
stolos.egg-info/PKG-INFO
stolos.egg-info/SOURCES.txt
stolos.egg-info/dependency_links.txt
stolos.egg-info/entry_points.txt
stolos.egg-info/not-zip-safe
stolos.egg-info/requires.txt
stolos.egg-info/top_level.txt
stolos/configuration_backend/__init__.py
stolos/configuration_backend/json_config.py
stolos/configuration_backend/redis_config.py
stolos/configuration_backend/tasks_config_base.py
stolos/dag_tools/__init__.py
stolos/dag_tools/build.py
stolos/dag_tools/node.py
stolos/dag_tools/traversal.py
stolos/examples/__init__.py
stolos/examples/job_id_validations.py
stolos/examples/valid_if_or_example.py
stolos/examples/tasks/__init__.py
stolos/examples/tasks/pyspark_example.py
stolos/examples/tasks/test_task.py
stolos/plugins/__init__.py
stolos/plugins/bash_plugin.py
stolos/plugins/pyspark_context.py
stolos/plugins/pyspark_plugin.py
stolos/queue_backend/__init__.py
stolos/queue_backend/locking.py
stolos/queue_backend/modify_job_state.py
stolos/queue_backend/qbcli_baseapi.py
stolos/queue_backend/qbcli_redis.py
stolos/queue_backend/qbcli_zookeeper.py
stolos/queue_backend/read_job_state.py
stolos/queue_backend/shared.py
stolos/testing_tools/__init__.py
stolos/testing_tools/queue_backend_validations.py
stolos/testing_tools/setup_funcs.py
stolos/testing_tools/with_setup_tools.py