Metadata-Version: 1.0
Name: stolos
Version: 2.0.1
Summary: A DAG-based job queueing system and executor for performing work with complex dependency requirements between applications
Home-page: https://github.com/sailthru/stolos
Author: Sailthru Data Science Team
Author-email: agaudio@sailthru.com
License: UNKNOWN
Keywords: stolos,scheduler,dag,directed acyclic graph,graph,data,dependency,queue,queueing system,pipeline,applications,machine learning,executor
Platform: UNKNOWN
